winaudio/__init__.py
winaudio/ctypes_binds.py
winaudio/exceptions.py
winaudio/flags.py
winaudio/player.py
winaudio/simple_playsound.py
winaudio/sound_mci.py
winaudio/tools.py
winaudio/wave_tools.py
winaudio/win_check.py
winaudio-1.0.6.dist-info/LICENSE
winaudio-1.0.6.dist-info/METADATA
winaudio-1.0.6.dist-info/WHEEL
winaudio-1.0.6.dist-info/top_level.txt
winaudio-1.0.6.dist-info/RECORD
