Metadata-Version: 2.1
Name: winaudio
Version: 1.0.6
Summary: Windows Audio API Bindings.
Home-page: https://github.com/Pixelsuft/winaudio
Author: Pixelsuft
License: MIT
Project-URL: Readme, https://github.com/Pixelsuft/winaudio/blob/main/README.MD
Project-URL: Example, https://github.com/Pixelsuft/winaudio/blob/main/main.py
Project-URL: Issue tracker, https://github.com/Pixelsuft/winaudio/issues
Keywords: winaudio
Platform: UNKNOWN
Classifier: License :: OSI Approved :: MIT License
Classifier: Programming Language :: Python :: 3.6
Classifier: Programming Language :: Python :: 3.7
Classifier: Programming Language :: Python :: 3.8
Classifier: Programming Language :: Python :: 3.9
Requires-Python: >=3.6
License-File: LICENSE
